{
  "basePlayerCards": [
    {
      "category": "Тезис",
      "name": "Кофе для мозга",
      "effect": "logic",
      "damage": 2,
      "text": "Кофе улучшает концентрацию, это доказано наукой!",
      "desc": "Утверждение про пользу.",
      "usesLeft": 3,
      "used": false,
      "fromDiscard": false
    },
    {
      "category": "Тезис",
      "name": "Кофе для души",
      "effect": "emotion",
      "damage": 2,
      "text": "Кофе поднимает настроение, это факт!",
      "desc": "Утверждение про чувства.",
      "usesLeft": 3,
      "used": false,
      "fromDiscard": false
    }
  ],
  "baseEnemyCards": [
    {
      "category": "Тезис",
      "name": "Кофе как яд",
      "effect": "logic",
      "damage": 2,
      "text": "Кофе вреден для сердца, исследования это подтверждают!",
      "desc": "Утверждение про вред.",
      "usesLeft": 3,
      "used": false,
      "fromDiscard": false
    },
    {
      "category": "Тезис",
      "name": "Кофе как цепи",
      "effect": "emotion",
      "damage": 2,
      "text": "Кофе вызывает зависимость, как любой наркотик!",
      "desc": "Утверждение про чувства.",
      "usesLeft": 3,
      "used": false,
      "fromDiscard": false
    }
  ],
  "specialCards": {
    "repeatCard": {
      "category": "Замечание",
      "name": "Повторение",
      "effect": "none",
      "damage": 0,
      "text": "Ты уже это говорил!",
      "desc": "Обнуляет ход.",
      "used": false,
      "fromDiscard": false
    },
    "observationCard": {
      "category": "Замечание",
      "name": "Растерянность",
      "effect": "random",
      "damage": 2,
      "text": "Ты совсем растерялся, да?",
      "desc": "Усугубляет слабость.",
      "used": false,
      "fromDiscard": false
    },
    "critiqueCard": {
      "category": "Укол",
      "name": "Противоречие",
      "effect": "random",
      "damage": 3,
      "text": "Твои слова не сходятся!",
      "desc": "Атака с риском (-2 тебе при неудаче).",
      "used": false,
      "fromDiscard": false,
      "risk": 0.3
    }
  },
  "reflectionCards": {
    "logic": {
      "category": "Размышление",
      "name": "Переосмысление",
      "effect": "logic",
      "heal": 3,
      "text": "Хотя, если подумать, есть исследования за кофе…",
      "desc": "Восстанавливает логику.",
      "used": false,
      "fromDiscard": false
    },
    "emotion": {
      "category": "Размышление",
      "name": "Спокойствие",
      "effect": "emotion",
      "heal": 3,
      "text": "Я всё же спокоен, кофе помогает.",
      "desc": "Восстанавливает эмоции.",
      "used": false,
      "fromDiscard": false
    }
  },
  "rareAttackCards": [
    {
      "category": "Тезис",
      "name": "Упрямство",
      "effect": "emotion",
      "damage": 3,
      "text": "Ты просто упрям, кофе — это жизнь!",
      "desc": "Сильное утверждение про чувства.",
      "used": false,
      "fromDiscard": false
    },
    {
      "category": "Тезис",
      "name": "Бзик",
      "effect": "logic",
      "damage": 3,
      "text": "Твой страх кофе — это бзик!",
      "desc": "Сильное утверждение про логику.",
      "used": false,
      "fromDiscard": false
    }
  ],
  "counterCards": [
    {
      "category": "Контраргумент",
      "name": "Спорные данные",
      "effect": "logic",
      "damage": 2,
      "text": "Да, но исследования про кофе спорные!",
      "desc": "Оспаривает логику.",
      "used": false,
      "fromDiscard": false
    },
    {
      "category": "Контраргумент",
      "name": "Преувеличение",
      "effect": "emotion",
      "damage": 2,
      "text": "Ты преувеличиваешь, это не так страшно!",
      "desc": "Оспаривает эмоции.",
      "used": false,
      "fromDiscard": false
    }
  ],
  "derivativeTemplates": [
    {
      "suffix": "+ Факты",
      "damageBonus": 0,
      "heal": 1,
      "textSuffix": " И это факт!",
      "desc": "Утверждение с защитой."
    },
    {
      "suffix": "+ Жар",
      "damageBonus": 1,
      "heal": 0,
      "textSuffix": " Сказано с жаром!",
      "desc": "Усиленное утверждение."
    }
  ]
}